{
  "uuid": "d55e73d7-85f1-4e98-bf4f-8f333a4eef31",
  "shortName": "Discover",
  "longName": "Discover",
  "companyName": "MakeAwesomeHappen",
  "versionLabel": "1.0",
  "sdkVersion": "3",
  "capabilities": [ "configurable" ],
  "targetPlatforms": ["aplite", "basalt", "chalk"],
  "enableMultiJS": true,
  "watchapp": {
    "watchface": false
  },
  "appKeys": {
    "KEY_LAT": 0,
    "KEY_LONG": 1,
    "KEY_DIFF": 2
  },
  "resources": {
    "media": [
      {
        "type": "png",
        "name": "ICON",
        "file": "images/icon.png",
        "menuIcon": true
      }
    ]
  }
}
